{
    "status_code": "200",
    "msg":"请求成功",
    "data":{
	    "time": 1449652239,
	    "data":[
	 		{"runId":"1","workTitle":"请教审批2015-10-10"},
	 		{"runId":"2","workTitle":"请教审批2015-10-11"},
	 		{"runId":"3","workTitle":"请教审批2015-10-12"},
	 		{"runId":"4","workTitle":"请教审批2015-10-13"},
	 		{"runId":"5","workTitle":"请教审批2015-10-14"},
	 		{"runId":"6","workTitle":"请教审批2015-10-15"},
	 		{"runId":"7","workTitle":"请教审批2015-10-16"},
	 		{"runId":"8","workTitle":"请教审批2015-10-17"},
	 		{"runId":"9","workTitle":"请教审批2015-10-18"},
	 		{"runId":"10","workTitle":"请教审批2015-10-19"},
	 		{"runId":"11","workTitle":"请教审批2015-10-20"},
	 		{"runId":"12","workTitle":"请教审批2015-10-21"},
	 		{"runId":"13","workTitle":"请教审批2015-10-22"},
	 		{"runId":"14","workTitle":"请教审批2015-10-23"},
	 		{"runId":"15","workTitle":"请教审批2015-10-24"},
	 		{"runId":"16","workTitle":"请教审批2015-10-25"},
	 		{"runId":"17","workTitle":"请教审批2015-10-26"},
	 		{"runId":"18","workTitle":"请教审批2015-10-27"},
	 		{"runId":"19","workTitle":"请教审批2015-10-28"}   	
	    ]
    }
}