{
	"status_code":"200",
    "msg":"请求成功",
    "data":{
    	"time":1449662771,
    	"data":{
			"common":[
				{"flowId":"1","flowName":"请假申请"},
				{"flowId":"2","flowName":"测试"},
				{"flowId":"3","flowName":"请假申请2"},
				{"flowId":"4","flowName":"测试3"},
				{"flowId":"5","flowName":"请假申请4"},
				{"flowId":"6","flowName":"测试5"}
			],
			"all":[
				{"flowId":"1","flowName":"请假申请"},
				{"flowId":"2","flowName":"测试"},
				{"flowId":"3","flowName":"费用报销"},
				{"flowId":"3","flowName":"请假申请2"},
				{"flowId":"4","flowName":"测试3"},
				{"flowId":"5","flowName":"请假申请4"},
				{"flowId":"6","flowName":"测试5"},
				{"flowId":"7","flowName":"请假申请6"},
				{"flowId":"8","flowName":"测试7"},
				{"flowId":"9","flowName":"请假申请8"},
				{"flowId":"10","flowName":"测试9"}
			]
		}
    }
}
